Metadata-Version: 2.1
Name: transfershpy
Version: 1.1
Summary: Use transfer.sh in python
Home-page: https://github.com/RinkaGI/transfer.py
Download-URL: https://github.com/RinkaGI/transfer.py/tarball/1.1
Author: RinkaDev
Author-email: rinkadevoficial@gmail.com
License: MIT
Keywords: transfer,upload,cloud
License-File: LICENSE
